btcpriceticker/__init__.py
btcpriceticker/_version.py
btcpriceticker/binance.py
btcpriceticker/bit2me.py
btcpriceticker/bitvavo.py
btcpriceticker/cli.py
btcpriceticker/coinbase.py
btcpriceticker/coingecko.py
btcpriceticker/coinpaprika.py
btcpriceticker/kraken.py
btcpriceticker/mempool.py
btcpriceticker/price.py
btcpriceticker/price_timeseries.py
btcpriceticker/service.py
btcpriceticker-0.3.1.dist-info/licenses/LICENSE
btcpriceticker-0.3.1.dist-info/METADATA
btcpriceticker-0.3.1.dist-info/WHEEL
btcpriceticker-0.3.1.dist-info/entry_points.txt
btcpriceticker-0.3.1.dist-info/top_level.txt
btcpriceticker-0.3.1.dist-info/RECORD
