Metadata-Version: 2.4
Name: btcpriceticker
Version: 0.3.1
Summary: Python lib for getting the bitcoin price
Author-email: Holger Nahrstaedt <nahrstaedt@gmail.com>
License: MIT License
Project-URL: Homepage, https://github.com/holgern/btcpriceticker
Keywords: price,btc,ticker
Classifier: Intended Audience :: Developers
Classifier: License :: OSI Approved :: MIT License
Classifier: Operating System :: OS Independent
Classifier: Programming Language :: Python :: 3
Classifier: Programming Language :: Python :: 3.9
Classifier: Programming Language :: Python :: 3.10
Classifier: Programming Language :: Python :: 3.11
Classifier: Programming Language :: Python :: 3.12
Classifier: Programming Language :: Python :: 3.13
Classifier: Topic :: Software Development :: Libraries
Requires-Python: >3.8.0
License-File: LICENSE
Requires-Dist: urllib3
Requires-Dist: pycoingecko
Requires-Dist: coinpaprika-sdk
Requires-Dist: pymempool
Requires-Dist: pandas
Requires-Dist: ccxt
Requires-Dist: typer
Requires-Dist: rich
Requires-Dist: requests
Dynamic: license-file
